bico/__init__.py
bico/_core.cpp
bico/base/algorithm.h
bico/base/attributecalculator.h
bico/base/clusterdissimilaritymeasure.h
bico/base/clustermeasuresetter.h
bico/base/combinedevaluation.h
bico/base/discreteboundedspace.h
bico/base/discreteproxyprovider.h
bico/base/dissimilaritymeasure.h
bico/base/euclideanspaceprovider.h
bico/base/evaluation.h
bico/base/inputsetter.h
bico/base/measuresetter.h
bico/base/partitionevaluation.h
bico/base/partitionprovider.h
bico/base/proxyevaluation.h
bico/base/proxygenerator.h
bico/base/proxyprovider.h
bico/base/solutionprovider.h
bico/base/streamingalgorithm.h
bico/base/weightedobject.h
bico/base/weightmodifier.h
bico/clustering/bico.h
bico/clustering/cfentry.h
bico/clustering/cfrentry.h
bico/core.py
bico/datastructure/discreteproxysolution.h
bico/datastructure/proxysolution.h
bico/evaluation/kmeansevaluator.h
bico/exception/clueexception.h
bico/exception/invalidargumentexception.h
bico/exception/invalidruntimeconfigurationexception.h
bico/point/l2metric.cpp
bico/point/l2metric.h
bico/point/point.cpp
bico/point/point.h
bico/point/pointcentroid.cpp
bico/point/pointcentroid.h
bico/point/pointweightmodifier.h
bico/point/realspaceprovider.cpp
bico/point/realspaceprovider.h
bico/point/squaredl2metric.cpp
bico/point/squaredl2metric.h
bico/_core.cpython-310-x86_64-linux-gnu.so
bico-0.1.2.dist-info/LICENSE
bico-0.1.2.dist-info/METADATA
bico-0.1.2.dist-info/WHEEL
bico-0.1.2.dist-info/RECORD
