Metadata-Version: 2.1
Name: bico
Version: 0.1.2
Summary: BICO is a fast streaming algorithm to compute coresets for the k-means problem on very large sets of points.
Author: Melanie Schmidt
Author-email: mschmidt@hhu.de
Requires-Python: >=3.9,<4.0
Classifier: Programming Language :: Python :: 3
Classifier: Programming Language :: Python :: 3.9
Classifier: Programming Language :: Python :: 3.10
Classifier: Programming Language :: Python :: 3.11
Classifier: Programming Language :: Python :: 3.12
Requires-Dist: numpy (>=1.26.4,<2.0.0)
Requires-Dist: scikit-learn (>=1.5.0,<2.0.0)
